yippi/__init__.py
yippi/AbstractYippi.py
yippi/AsyncYippi.py
yippi/Classes.py
yippi/Constants.py
yippi/Enums.py
yippi/Exceptions.py
yippi/YippiSync.py
yippi-0.2.0.1.dist-info/LICENSE
yippi-0.2.0.1.dist-info/WHEEL
yippi-0.2.0.1.dist-info/METADATA
yippi-0.2.0.1.dist-info/RECORD
