Metadata-Version: 2.1
Name: yippi
Version: 0.2.0.1
Summary: An (a)sync e621 API wrapper for Python.
Home-page: https://github.com/rorre/Yippi
License: LGPL-3.0-only
Author: Rendy Arya Kemal
Author-email: rendyarya22@gmail.com
Requires-Python: >=3.7,<4.0
Classifier: Development Status :: 5 - Production/Stable
Classifier: Intended Audience :: Developers
Classifier: License :: OSI Approved :: GNU Lesser General Public License v3 (LGPLv3)
Classifier: Operating System :: Microsoft :: Windows
Classifier: Operating System :: POSIX
Classifier: Operating System :: Unix
Classifier: Programming Language :: Python
Classifier: Programming Language :: Python :: 3
Classifier: Programming Language :: Python :: 3.7
Classifier: Programming Language :: Python :: 3.8
Classifier: Programming Language :: Python :: 3.9
Classifier: Programming Language :: Python :: Implementation :: CPython
Classifier: Programming Language :: Python :: Implementation :: PyPy
Classifier: Topic :: Utilities
Requires-Dist: Sphinx[docs] (>=4.0.2,<5.0.0)
Requires-Dist: aiohttp (>=3.6.2,<4.0.0)
Requires-Dist: pyrate-limiter (>=2.3.4,<3.0.0)
Requires-Dist: requests (>=2.23.0,<3.0.0)
Requires-Dist: sphinx-rtd-theme[docs] (>=0.5.2,<0.6.0)
Requires-Dist: sphinxcontrib-napoleon[docs] (>=0.7,<0.8)
Project-URL: Documentation, https://yippi.readthedocs.io/
Project-URL: Repository, https://github.com/rorre/Yippi
